aserto/client/__init__.py
aserto/client/_deadline.py
aserto/client/authorizer/__init__.py
aserto/client/authorizer/aio/__init__.py
aserto/client/authorizer/helpers.py
aserto/client/directory/__init__.py
aserto/client/directory/aio/__init__.py
aserto/client/directory/channels.py
aserto/client/directory/v3/__init__.py
aserto/client/directory/v3/aio/__init__.py
aserto/client/directory/v3/helpers.py
aserto/client/identity.py
aserto/client/options.py
aserto/client/py.typed
aserto/client/resource_context.py
aserto-0.32.2.dist-info/LICENSE
aserto-0.32.2.dist-info/METADATA
aserto-0.32.2.dist-info/WHEEL
aserto-0.32.2.dist-info/RECORD
