Metadata-Version: 2.3
Name: aserto
Version: 0.32.2
Summary: Aserto API client
License: Apache-2.0
Author: Aserto, Inc.
Author-email: pypi@aserto.com
Maintainer: authereal
Maintainer-email: authereal@aserto.com
Requires-Python: >=3.9,<4.0
Classifier: Intended Audience :: Developers
Classifier: License :: OSI Approved :: Apache Software License
Classifier: Operating System :: OS Independent
Classifier: Programming Language :: Python
Classifier: Programming Language :: Python :: 3
Classifier: Programming Language :: Python :: 3.9
Classifier: Programming Language :: Python :: 3.10
Classifier: Programming Language :: Python :: 3.11
Classifier: Programming Language :: Python :: 3.12
Classifier: Programming Language :: Python :: 3.13
Classifier: Programming Language :: Python :: 3 :: Only
Classifier: Topic :: Software Development :: Libraries
Classifier: Typing :: Typed
Requires-Dist: aiohttp (>=3.10.2,<4.0.0)
Requires-Dist: aserto-authorizer (>=0.20.7,<0.21.0)
Requires-Dist: aserto-directory (>=0.33.8,<0.34.0)
Project-URL: Documentation, https://github.com/aserto-dev/aserto-python/tree/HEAD
Project-URL: Homepage, https://github.com/aserto-dev/aserto-python/tree/HEAD
Project-URL: Repository, https://github.com/aserto-dev/aserto-python/tree/HEAD
